pandoraref/__init__.py
pandoraref/data/external/fov_distortion.csv
pandoraref/data/external/vega.csv
pandoraref/data/nirda/badpix.fits
pandoraref/data/nirda/bias.fits
pandoraref/data/nirda/dark.fits
pandoraref/data/nirda/flat.fits
pandoraref/data/nirda/gain.fits
pandoraref/data/nirda/nonlin.fits
pandoraref/data/nirda/pixel_position.fits
pandoraref/data/nirda/prf.fits
pandoraref/data/nirda/qe.fits
pandoraref/data/nirda/readnoise.fits
pandoraref/data/nirda/sip.fits
pandoraref/data/nirda/spectrum_normalization.fits
pandoraref/data/nirda/throughput.fits
pandoraref/data/nirda/wcs.fits
pandoraref/data/visda/badpix.fits
pandoraref/data/visda/bias.fits
pandoraref/data/visda/dark.fits
pandoraref/data/visda/flat.fits
pandoraref/data/visda/gain.fits
pandoraref/data/visda/nonlin.fits
pandoraref/data/visda/prf.fits
pandoraref/data/visda/qe.fits
pandoraref/data/visda/readnoise.fits
pandoraref/data/visda/sip.fits
pandoraref/data/visda/throughput.fits
pandoraref/data/visda/wcs.fits
pandoraref/dummy.py
pandoraref/ref.py
pandoraref/wcs.py
pandoraref-0.3.0.dist-info/METADATA
pandoraref-0.3.0.dist-info/WHEEL
pandoraref-0.3.0.dist-info/licenses/LICENSE
pandoraref-0.3.0.dist-info/RECORD
