Metadata-Version: 2.4
Name: pandoraref
Version: 0.3.0
Summary: 
License-File: LICENSE
Author: Christina Hedges
Author-email: christina.l.hedges@nasa.gov
Requires-Python: >=3.9,<3.13
Classifier: Programming Language :: Python :: 3
Classifier: Programming Language :: Python :: 3.9
Classifier: Programming Language :: Python :: 3.10
Classifier: Programming Language :: Python :: 3.11
Classifier: Programming Language :: Python :: 3.12
Requires-Dist: appdirs (>=1.4.4,<2.0.0)
Requires-Dist: astropy (>=6.0.0)
Requires-Dist: numpy (>=1.2)
Requires-Dist: pandas (>=2.2.3,<3.0.0)
Requires-Dist: rich (>=13.9.4,<14.0.0)
